MANIFEST.in
README.md
setup.cfg
setup.py
scope_injected_contextmanager/__init__.py
scope_injected_contextmanager.egg-info/PKG-INFO
scope_injected_contextmanager.egg-info/SOURCES.txt
scope_injected_contextmanager.egg-info/dependency_links.txt
scope_injected_contextmanager.egg-info/not-zip-safe
scope_injected_contextmanager.egg-info/top_level.txt
tests/__init__.py
tests/conftest.py
tests/test_all.py