Metadata-Version: 2.1
Name: scope-injected-contextmanager
Version: 0.0.2
Summary: A decorator/context manager that injects scope vars into a function
Home-page: https://github.com/sloev/scope_injected_contextmanager
Author: sloev
Author-email: johannes.valbjorn@gmail.com
License: UNKNOWN
Keywords: contextmanager decorator scope inject
Platform: UNKNOWN
Classifier: Development Status :: 6 - Mature
Classifier: Intended Audience :: Developers
Classifier: Natural Language :: English
Classifier: Programming Language :: Python :: 3.6
Classifier: Programming Language :: Python :: 3.7
Classifier: Programming Language :: Python :: 3.8
